altunityrunner/__init__.py
altunityrunner/altUnityExceptions.py
altunityrunner/runner.py
altunityrun-1.2.2.dist-info/LICENSE
altunityrun-1.2.2.dist-info/METADATA
altunityrun-1.2.2.dist-info/WHEEL
altunityrun-1.2.2.dist-info/top_level.txt
altunityrun-1.2.2.dist-info/RECORD
