Metadata-Version: 2.1
Name: altunityrun
Version: 1.2.2
Summary: Python Binding to allow Appium tests to be run against Unity games and apps using AltUnityTester
Home-page: https://gitlab.com/Vingithub93/unityautomation
Author: Unity Testing
Author-email: vinayakpatil.sw@gmail.com
License: GNU General Public License v3.0
Platform: UNKNOWN
